monitoring_as_code/__init__.py
monitoring_as_code/binds/__init__.py
monitoring_as_code/binds/grafana/__init__.py
monitoring_as_code/binds/grafana/client/__init__.py
monitoring_as_code/binds/grafana/client/alert_queries/__init__.py
monitoring_as_code/binds/grafana/client/alert_queries/classic_conditions.py
monitoring_as_code/binds/grafana/client/alert_queries/queries.py
monitoring_as_code/binds/grafana/client/alerting.py
monitoring_as_code/binds/grafana/client/base.py
monitoring_as_code/binds/grafana/client/types.py
monitoring_as_code/binds/grafana/grafana_provider.py
monitoring_as_code/binds/grafana/handlers/__init__.py
monitoring_as_code/binds/grafana/handlers/alert.py
monitoring_as_code/binds/grafana/handlers/folder.py
monitoring_as_code/binds/grafana/handlers/rule_group.py
monitoring_as_code/binds/grafana/objects/__init__.py
monitoring_as_code/binds/grafana/objects/alert.py
monitoring_as_code/binds/grafana/objects/base.py
monitoring_as_code/binds/grafana/objects/folder.py
monitoring_as_code/binds/grafana/utils.py
monitoring_as_code/controller/__init__.py
monitoring_as_code/controller/diff_utils.py
monitoring_as_code/controller/exceptions.py
monitoring_as_code/controller/handler.py
monitoring_as_code/controller/monitor.py
monitoring_as_code/controller/obj.py
monitoring_as_code/controller/provider.py
monitoring_as_code/controller/resource.py
monitoring_as_code/controller/state.py
monitoring_as_code/controller/states/__init__.py
monitoring_as_code/controller/states/file.py
monitoring_as_code/controller/utils.py
monitoring_as_code/py.typed
monitoring_as_code-0.0.2.dist-info/WHEEL
monitoring_as_code-0.0.2.dist-info/METADATA
monitoring_as_code-0.0.2.dist-info/RECORD
