Metadata-Version: 2.1
Name: monitoring-as-code
Version: 0.0.2
Summary: A monitoring as code approach library
Home-page: https://github.com/WinnerOK/monitoring-as-code
Keywords: monitoring-as-code,monitoring-configuration
Author: Daniil Manakovskiy
Author-email: d.manakovskiy@gmail.com
Requires-Python: >=3.10,<4.0
Classifier: Development Status :: 4 - Beta
Classifier: Intended Audience :: Developers
Classifier: Intended Audience :: System Administrators
Classifier: Programming Language :: Python :: 3
Classifier: Programming Language :: Python :: 3.10
Classifier: Topic :: Utilities
Requires-Dist: durationpy (>=0.5,<0.6)
Requires-Dist: loguru (>=0.6.0,<0.7.0)
Requires-Dist: pydantic (>=1.9.0,<2.0.0)
Requires-Dist: requests (>=2.27.1,<3.0.0)
Requires-Dist: retry (>=0.9.2,<0.10.0)
Project-URL: Repository, https://github.com/WinnerOK/monitoring-as-code
